monty_nats/__init__.py
monty_nats/jetstream-example.py
monty_nats/nats_wrapper.py
monty_nats-0.1.0.dist-info/licenses/LICENSE
monty_nats-0.1.0.dist-info/METADATA
monty_nats-0.1.0.dist-info/WHEEL
monty_nats-0.1.0.dist-info/top_level.txt
monty_nats-0.1.0.dist-info/RECORD
