Metadata-Version: 2.4
Name: monty-nats
Version: 0.1.0
Summary: A NATS helper used by Aity Monty
Home-page: https://github.com/rancher/monty-nats-wrapper
Author: Aity Cloud
Author-email: sanjay.nadhavajhala@suse.com
Project-URL: Bug Tracker, https://github.com/rancher/monty-nats-wrapper/issues
Classifier: Programming Language :: Python :: 3
Classifier: License :: OSI Approved :: Apache Software License
Classifier: Operating System :: OS Independent
Requires-Python: >=3.6
License-File: LICENSE
Requires-Dist: nats-py>=2.2.0
Requires-Dist: nkeys
Dynamic: license-file
